{"cameraMode":{"drawMode":0,"name":"Shaded","section":"Shading Mode"},"sceneLighting":true,"audioPlay":false,"sceneViewState":{"m_AlwaysRefresh":false,"showFog":true,"showSkybox":true,"showFlares":true,"showImageEffects":true,"showParticleSystems":true,"showVisualEffectGraphs":true,"m_FxEnabled":true},"in2DMode":false,"pivot":{"x":1244.6624755859375,"y":411.41461181640627,"z":53.8624267578125},"rotation":{"x":-0.14175087213516236,"y":0.061526112258434299,"z":-0.008820651099085808,"w":-0.9879840016365051},"size":722.8818359375,"orthographic":false}